spongetext/__init__.py
spongetext/__main__.py
spongetext/spongestring.py
spongetext-1.0.0.dist-info/METADATA
spongetext-1.0.0.dist-info/WHEEL
spongetext-1.0.0.dist-info/top_level.txt
spongetext-1.0.0.dist-info/RECORD
