Metadata-Version: 2.1
Name: spongetext
Version: 1.0.0
Summary: Creates text with randomly capitalized letters.
Home-page: https://github.com/jwizzle/spongetext
Author: j wizzle
Author-email: info@hossel.net
License: UNKNOWN
Platform: UNKNOWN
Classifier: Programming Language :: Python :: 3
Classifier: License :: OSI Approved :: MIT License
Classifier: Operating System :: OS Independent
Requires-Python: >=3.6
